{
		"bronze": {"top": "1402",
			  "jungle": "1358", 
			  "mid": "1337",
			  "adc": "1177",
			  "support": "1505"},
		"silver": {"top": "3362",
			  "jungle": "3497", 
			  "mid": "3378",
			  "adc": "3293",
			  "support": "3598"},
		"gold": {"top": "2262",
			  "jungle": "2329", 
			  "mid": "2245",
			  "adc": "2115",
			  "support": "2364"},
		"platinum": {"top": "838",
			  "jungle": "869", 
			  "mid": "885",
			  "adc": "815",
			  "support": "844"},
		"diamond": {"top": "339",
			  "jungle": "316", 
			  "mid": "346",
			  "adc": "327",
			  "support": "327"},
		"master": {"top": "16",
			  "jungle": "12", 
			  "mid": "18",
			  "adc": "12",
			  "support": "18"},
		"challenger": {"top": "3",
			  "jungle": "3", 
			  "mid": "1",
			  "adc": "3",
			  "support": "1"},
		"unranked": {"top": "1699",
			  "jungle": "1836", 
			  "mid": "1752",
			  "adc": "1577",
			  "support": "1875"}
	}