{
		"bronze": {"top": {"athenes": "16",
				"liandrys": "95",
				"ludens": "95",
				"morello":"53",
				"nashors": "27",
				"roa": "185",
				"seraphs": "10",
				"rabadons": "103",
				"rylais": "68",
				"void": "42",
				"woa": "70",
				"zhonyas": "153"},
			"jungle": {"athenes": "3",
				"liandrys": "39",
				"ludens": "62",
				"morello":"21",
				"nashors": "33",
				"roa": "49",
				"seraphs": "0",
				"rabadons": "58",
				"rylais": "32",
				"void": "34",
				"woa": "2",
				"zhonyas": "108"},
			"mid": {"athenes": "173",
				"liandrys": "103",
				"ludens": "875",
				"morello":"486",
				"nashors": "51",
				"roa": "235",
				"seraphs": "24",
				"rabadons": "697",
				"rylais": "114",
				"void": "262",
				"woa": "57",
				"zhonyas": "734"},
			"adc": {"athenes": "0",
				"liandrys": "1",
				"ludens": "5",
				"morello":"2",
				"nashors": "1",
				"roa": "1",
				"seraphs": "0",
				"rabadons": "3",
				"rylais": "0",
				"void": "1",
				"woa": "0",
				"zhonyas": "3"},
			"support": {"athenes": "61",
				"liandrys": "29",
				"ludens": "129",
				"morello":"118",
				"nashors": "6",
				"roa": "76",
				"seraphs": "6",
				"rabadons": "118",
				"rylais": "49",
				"void": "35",
				"woa": "3",
				"zhonyas": "225"}},
		"silver": {"top": {"athenes": "7",
				"liandrys": "132",
				"ludens": "85",
				"morello":"58",
				"nashors": "41",
				"roa": "254",
				"seraphs": "9",
				"rabadons": "117",
				"rylais": "113",
				"void": "61",
				"woa": "129",
				"zhonyas": "237"},
			"jungle": {"athenes": "7",
				"liandrys": "68",
				"ludens": "103",
				"morello":"19",
				"nashors": "26",
				"roa": "85",
				"seraphs": "1",
				"rabadons": "94",
				"rylais": "52",
				"void": "50",
				"woa": "5",
				"zhonyas": "135"},
			"mid": {"athenes": "261",
				"liandrys": "118",
				"ludens": "1082",
				"morello":"680",
				"nashors": "48",
				"roa": "275",
				"seraphs": "27",
				"rabadons": "826",
				"rylais": "157",
				"void": "357",
				"woa": "49",
				"zhonyas": "910"},
			"adc": {"athenes": "0",
				"liandrys": "0",
				"ludens": "4",
				"morello":"1",
				"nashors": "1",
				"roa": "0",
				"seraphs": "0",
				"rabadons": "3",
				"rylais": "1",
				"void": "2",
				"woa": "0",
				"zhonyas": "3"},
			"support": {"athenes": "43",
				"liandrys": "24",
				"ludens": "103",
				"morello":"104",
				"nashors": "7",
				"roa": "73",
				"seraphs": "5",
				"rabadons": "71",
				"rylais": "54",
				"void": "34",
				"woa": "0",
				"zhonyas": "238"}},
		"gold": {"top": {"athenes": "9",
				"liandrys": "77",
				"ludens": "35",
				"morello":"31",
				"nashors": "13",
				"roa": "126",
				"seraphs": "2",
				"rabadons": "63",
				"rylais": "75",
				"void": "35",
				"woa": "80",
				"zhonyas": "132"},
			"jungle": {"athenes": "2",
				"liandrys": "52",
				"ludens": "69",
				"morello":"17",
				"nashors": "18",
				"roa": "45",
				"seraphs": "1",
				"rabadons": "52",
				"rylais": "49",
				"void": "22",
				"woa": "1",
				"zhonyas": "94"},
			"mid": {"athenes": "155",
				"liandrys": "58",
				"ludens": "556",
				"morello":"396",
				"nashors": "16",
				"roa": "128",
				"seraphs": "4",
				"rabadons": "427",
				"rylais": "84",
				"void": "180",
				"woa": "14",
				"zhonyas": "500"},
			"adc": {"athenes": "0",
				"liandrys": "0",
				"ludens": "0",
				"morello":"0",
				"nashors": "0",
				"roa": "0",
				"seraphs": "0",
				"rabadons": "0",
				"rylais": "0",
				"void": "0",
				"woa": "0",
				"zhonyas": "0"},
			"support": {"athenes": "20",
				"liandrys": "13",
				"ludens": "51",
				"morello":"49",
				"nashors": "2",
				"roa": "23",
				"seraphs": "2",
				"rabadons": "32",
				"rylais": "23",
				"void": "10",
				"woa": "0",
				"zhonyas": "116"}},
		"platinum": {"top": {"athenes": "3",
				"liandrys": "35",
				"ludens": "20",
				"morello":"17",
				"nashors": "4",
				"roa": "49",
				"seraphs": "0",
				"rabadons": "26",
				"rylais": "29",
				"void": "16",
				"woa": "31",
				"zhonyas": "66"},
			"jungle": {"athenes": "3",
				"liandrys": "25",
				"ludens": "19",
				"morello":"6",
				"nashors": "15",
				"roa": "21",
				"seraphs": "0",
				"rabadons": "23",
				"rylais": "28",
				"void": "11",
				"woa": "0",
				"zhonyas": "42"},
			"mid": {"athenes": "71",
				"liandrys": "19",
				"ludens": "263",
				"morello":"208",
				"nashors": "6",
				"roa": "51",
				"seraphs": "6",
				"rabadons": "225",
				"rylais": "39",
				"void": "98",
				"woa": "9",
				"zhonyas": "258"},
			"adc": {"athenes": "0",
				"liandrys": "0",
				"ludens": "0",
				"morello":"0",
				"nashors": "0",
				"roa": "0",
				"seraphs": "0",
				"rabadons": "0",
				"rylais": "0",
				"void": "0",
				"woa": "0",
				"zhonyas": "2"},
			"support": {"athenes": "3",
				"liandrys": "3",
				"ludens": "13",
				"morello":"18",
				"nashors": "1",
				"roa": "6",
				"seraphs": "1",
				"rabadons": "8",
				"rylais": "8",
				"void": "4",
				"woa": "1",
				"zhonyas": "34"}},
		"diamond": {"top": {"athenes": "0",
				"liandrys": "11",
				"ludens": "3",
				"morello":"6",
				"nashors": "1",
				"roa": "18",
				"seraphs": "1",
				"rabadons": "9",
				"rylais": "7",
				"void": "8",
				"woa": "6",
				"zhonyas": "26"},
			"jungle": {"athenes": "0",
				"liandrys": "11",
				"ludens": "10",
				"morello":"1",
				"nashors": "4",
				"roa": "8",
				"seraphs": "0",
				"rabadons": "10",
				"rylais": "16",
				"void": "10",
				"woa": "0",
				"zhonyas": "21"},
			"mid": {"athenes": "29",
				"liandrys": "13",
				"ludens": "91",
				"morello":"79",
				"nashors": "6",
				"roa": "12",
				"seraphs": "1",
				"rabadons": "75",
				"rylais": "18",
				"void": "48",
				"woa": "4",
				"zhonyas": "89"},
			"adc": {"athenes": "0",
				"liandrys": "0",
				"ludens": "3",
				"morello":"2",
				"nashors": "0",
				"roa": "0",
				"seraphs": "0",
				"rabadons": "0",
				"rylais": "0",
				"void": "2",
				"woa": "0",
				"zhonyas": "1"},
			"support": {"athenes": "1",
				"liandrys": "2",
				"ludens": "3",
				"morello":"7",
				"nashors": "0",
				"roa": "0",
				"seraphs": "0",
				"rabadons": "2",
				"rylais": "4",
				"void": "1",
				"woa": "0",
				"zhonyas": "9"}},
		"master": {"top": {"athenes": "0",
				"liandrys": "0",
				"ludens": "0",
				"morello":"0",
				"nashors": "0",
				"roa": "1",
				"seraphs": "0",
				"rabadons": "0",
				"rylais": "0",
				"void": "1",
				"woa": "0",
				"zhonyas": "1"},
			"jungle": {"athenes": "0",
				"liandrys": "0",
				"ludens": "1",
				"morello":"1",
				"nashors": "0",
				"roa": "1",
				"seraphs": "0",
				"rabadons": "0",
				"rylais": "0",
				"void": "0",
				"woa": "0",
				"zhonyas": "1"},
			"mid": {"athenes": "0",
				"liandrys": "0",
				"ludens": "2",
				"morello":"4",
				"nashors": "0",
				"roa": "0",
				"seraphs": "0",
				"rabadons": "4",
				"rylais": "0",
				"void": "1",
				"woa": "1",
				"zhonyas": "3"},
			"adc": {"athenes": "0",
				"liandrys": "0",
				"ludens": "0",
				"morello":"0",
				"nashors": "0",
				"roa": "0",
				"seraphs": "0",
				"rabadons": "0",
				"rylais": "0",
				"void": "0",
				"woa": "0",
				"zhonyas": "0"},
			"support": {"athenes": "0",
				"liandrys": "0",
				"ludens": "0",
				"morello":"0",
				"nashors": "0",
				"roa": "0",
				"seraphs": "0",
				"rabadons": "0",
				"rylais": "0",
				"void": "0",
				"woa": "0",
				"zhonyas": "0"}},
		"challenger": {"top": {"athenes": "0",
				"liandrys": "1",
				"ludens": "0",
				"morello":"0",
				"nashors": "0",
				"roa": "0",
				"seraphs": "0",
				"rabadons": "0",
				"rylais": "1",
				"void": "0",
				"woa": "0",
				"zhonyas": "1"},
			"jungle": {"athenes": "0",
				"liandrys": "0",
				"ludens": "0",
				"morello":"0",
				"nashors": "0",
				"roa": "0",
				"seraphs": "0",
				"rabadons": "0",
				"rylais": "0",
				"void": "0",
				"woa": "0",
				"zhonyas": "1"},
			"mid": {"athenes": "0",
				"liandrys": "0",
				"ludens": "1",
				"morello":"2",
				"nashors": "0",
				"roa": "0",
				"seraphs": "0",
				"rabadons": "1",
				"rylais": "1",
				"void": "2",
				"woa": "0",
				"zhonyas": "2"},
			"adc": {"athenes": "0",
				"liandrys": "0",
				"ludens": "0",
				"morello":"0",
				"nashors": "0",
				"roa": "0",
				"seraphs": "0",
				"rabadons": "0",
				"rylais": "0",
				"void": "0",
				"woa": "0",
				"zhonyas": "0"},
			"support": {"athenes": "0",
				"liandrys": "0",
				"ludens": "1",
				"morello":"0",
				"nashors": "0",
				"roa": "0",
				"seraphs": "0",
				"rabadons": "0",
				"rylais": "0",
				"void": "0",
				"woa": "0",
				"zhonyas": "1"}},
		"unranked": {"top": {"athenes": "9",
				"liandrys": "77",
				"ludens": "78",
				"morello":"58",
				"nashors": "39",
				"roa": "199",
				"seraphs": "7",
				"rabadons": "126",
				"rylais": "55",
				"void": "54",
				"woa": "71",
				"zhonyas": "189"},
			"jungle": {"athenes": "6",
				"liandrys": "37",
				"ludens": "81",
				"morello":"24",
				"nashors": "22",
				"roa": "53",
				"seraphs": "4",
				"rabadons": "67",
				"rylais": "42",
				"void": "26",
				"woa": "1",
				"zhonyas": "91"},
			"mid": {"athenes": "138",
				"liandrys": "69",
				"ludens": "859",
				"morello":"549",
				"nashors": "53",
				"roa": "254",
				"seraphs": "23",
				"rabadons": "724",
				"rylais": "115",
				"void": "243",
				"woa": "46",
				"zhonyas": "685"},
			"adc": {"athenes": "0",
				"liandrys": "1",
				"ludens": "6",
				"morello":"0",
				"nashors": "1",
				"roa": "2",
				"seraphs": "0",
				"rabadons": "3",
				"rylais": "1",
				"void": "2",
				"woa": "0",
				"zhonyas": "2"},
			"support": {"athenes": "56",
				"liandrys": "22",
				"ludens": "155",
				"morello":"120",
				"nashors": "9",
				"roa": "88",
				"seraphs": "7",
				"rabadons": "157",
				"rylais": "75",
				"void": "34",
				"woa": "3",
				"zhonyas": "282"}}
	}